expan/__init__.py
expan/error.py
expan/importer.py
expan/main.py
expan/preprocessor.py
pyml/__init__.py
pyml/activate.py
pyml/ast.py
pyml/component.py
pyml/elements.py
pyml/expander.py
pyml/macros.py
pyml/parsing.py
pyml/scaffold.py
pyml3-0.1.1.dist-info/METADATA
pyml3-0.1.1.dist-info/WHEEL
pyml3-0.1.1.dist-info/RECORD
