Metadata-Version: 2.1
Name: pyml3
Version: 0.1.1
Summary: Library for generating HTML through the use of syntactic macros in python
Author: stackswithans
Author-email: stexor12@gmail.com
Requires-Python: >=3.10,<4.0
Classifier: Programming Language :: Python :: 3
Classifier: Programming Language :: Python :: 3.10
Classifier: Programming Language :: Python :: 3.11
Requires-Dist: pyparsing (>=3.1.1,<4.0.0)
Requires-Dist: termcolor (==2.4.0)
